{
  "total_trades": 7,
  "winning_trades": 5,
  "losing_trades": 2,
  "win_rate": 71.428571,
  "gross_pnl": 164.852812,
  "fee": 44.119236,
  "slippage": 40.074599,
  "total_cost": 84.193835,
  "net_pnl": 80.658977,
  "avg_expected_edge_bps": 39.516461,
  "avg_actual_edge_bps": 13.213002,
  "avg_edge_realization_bps": -26.303459,
  "avg_total_cost_bps": 15.411398,
  "cost_to_gross_loss_ratio": 0.510721,
  "signals_generated": 7,
  "signals_preapproved": 7,
  "signals_rejected_initial_risk": 0,
  "signals_rejected_actual_entry": 0,
  "trades_opened": 7,
  "trades_closed": 7,
  "risk_rejections": 0,
  "dominant_rejection_reason": "",
  "dominant_rejection_count": 0
}
