{
  "total_trades": 54,
  "winning_trades": 15,
  "losing_trades": 39,
  "win_rate": 27.777778,
  "gross_pnl": -89.334199,
  "fee": 65.139012,
  "slippage": 0.000000,
  "total_cost": 65.139012,
  "net_pnl": -154.473211,
  "avg_expected_edge_bps": 115.276779,
  "avg_actual_edge_bps": -34.467521,
  "avg_edge_realization_bps": -149.744300,
  "avg_total_cost_bps": 10.012882,
  "cost_to_gross_loss_ratio": 0.729161,
  "signals_generated": 54,
  "signals_preapproved": 54,
  "signals_rejected_initial_risk": 0,
  "signals_rejected_actual_entry": 0,
  "trades_opened": 54,
  "trades_closed": 54,
  "risk_rejections": 0,
  "dominant_rejection_reason": "",
  "dominant_rejection_count": 0
}
