{
  "total_trades": 888,
  "winning_trades": 174,
  "losing_trades": 714,
  "win_rate": 19.594595,
  "gross_pnl": -973.901861,
  "fee": 1730.212195,
  "slippage": 2168.228580,
  "total_cost": 3898.440774,
  "net_pnl": -4872.342635,
  "avg_expected_edge_bps": 32.302185,
  "avg_actual_edge_bps": -22.586522,
  "avg_edge_realization_bps": -54.888707,
  "avg_total_cost_bps": 18.017529,
  "cost_to_gross_loss_ratio": 4.002909,
  "signals_generated": 1104,
  "signals_preapproved": 888,
  "signals_rejected_initial_risk": 216,
  "signals_rejected_actual_entry": 0,
  "trades_opened": 888,
  "trades_closed": 888,
  "risk_rejections": 216,
  "dominant_rejection_reason": "daily_loss_limit_reached",
  "dominant_rejection_count": 216
}
