{
  "total_trades": 308,
  "winning_trades": 74,
  "losing_trades": 234,
  "win_rate": 24.025974,
  "gross_pnl": -725.301511,
  "fee": 1150.193751,
  "slippage": 1423.847691,
  "total_cost": 2574.041443,
  "net_pnl": -3299.342953,
  "avg_expected_edge_bps": 35.247609,
  "avg_actual_edge_bps": -22.167822,
  "avg_edge_realization_bps": -57.415431,
  "avg_total_cost_bps": 17.801321,
  "cost_to_gross_loss_ratio": 3.548926,
  "signals_generated": 308,
  "signals_preapproved": 308,
  "signals_rejected_initial_risk": 0,
  "signals_rejected_actual_entry": 0,
  "trades_opened": 308,
  "trades_closed": 308,
  "risk_rejections": 0,
  "dominant_rejection_reason": "",
  "dominant_rejection_count": 0
}
